anagram_package/__init__.py
anagram_package/__main__.py
anagram_package/anagram.py
anagram_package/words.pkl
anagram_package-1.0.0.dist-info/licenses/LICENSE
anagram_package-1.0.0.dist-info/METADATA
anagram_package-1.0.0.dist-info/WHEEL
anagram_package-1.0.0.dist-info/entry_points.txt
anagram_package-1.0.0.dist-info/top_level.txt
anagram_package-1.0.0.dist-info/RECORD
