Metadata-Version: 2.4
Name: anagram_package
Version: 1.0.0
Summary: A package with fun functions for anagrams, pallidromes, and words with missing letters.
Author: Wyatt Destabelle, Nick Michael, Alan Chen, Isaac Fisher
License: MIT License
Project-URL: Homepage, https://github.com/software-students-spring2025/3-python-package-fedex-package-delivery-services
Project-URL: Repository, https://github.com/software-students-spring2025/3-python-package-fedex-package-delivery-services.git
Project-URL: Bug Tracker, https://github.com/software-students-spring2025/3-python-package-fedex-package-delivery-services/issues
Keywords: python,package
Requires-Python: >=3.7
License-File: LICENSE
Provides-Extra: dev
Requires-Dist: pytest; extra == "dev"
Dynamic: license-file
